twilio_phone_calls/__init__.py
twilio_phone_calls/twilio_phone_call.py
twilio_phone_calls/twilio_voice_response.py
twilio_phone_calls/audio/__init__.py
twilio_phone_calls/audio/audio_conversions.py
twilio_phone_calls/audio/audio_sample_buffer.py
twilio_phone_calls/audio/audio_stream_listener.py
twilio_phone_calls/audio/tmp_file_path.py
twilio_phone_calls/audio/voice_to_text.py
twilio_phone_calls/twilio_pydantic/__init__.py
twilio_phone_calls/twilio_pydantic/outgoing_mark_message.py
twilio_phone_calls/twilio_pydantic/outgoing_media_message.py
twilio_phone_calls/twilio_pydantic/outgoing_media_payload.py
twilio_phone_calls/twilio_pydantic/stream_connected_message.py
twilio_phone_calls/twilio_pydantic/stream_events_enum.py
twilio_phone_calls/twilio_pydantic/stream_mark_message.py
twilio_phone_calls/twilio_pydantic/stream_mark_payload.py
twilio_phone_calls/twilio_pydantic/stream_media_message.py
twilio_phone_calls/twilio_pydantic/stream_media_payload.py
twilio_phone_calls/twilio_pydantic/stream_start_custom_params.py
twilio_phone_calls/twilio_pydantic/stream_start_message.py
twilio_phone_calls/twilio_pydantic/stream_start_payload.py
twilio_phone_calls/twilio_pydantic/stream_stop_message.py
twilio_phone_calls/twilio_pydantic/twilio_stream_message.py
twilio_phone_calls-1.3.dist-info/LICENSE
twilio_phone_calls-1.3.dist-info/METADATA
twilio_phone_calls-1.3.dist-info/WHEEL
twilio_phone_calls-1.3.dist-info/top_level.txt
twilio_phone_calls-1.3.dist-info/RECORD
